{
  "annotations": {
    "list": [
      {
        "builtIn": 1,
        "datasource": "-- Grafana --",
        "enable": true,
        "hide": true,
        "iconColor": "rgba(0, 211, 255, 1)",
        "name": "Annotations & Alerts",
        "target": {
          "limit": 100,
          "matchAny": false,
          "tags": [],
          "type": "dashboard"
        },
        "type": "dashboard"
      },
      {
        "datasource": "prometheus",
        "enable": true,
        "iconColor": "#1f78b4",
        "name": "Deployments",
        "target": {
          "expr": "changes(deployment_timestamp[1h]) > 0",
          "legendFormat": "{{ service }} deployed",
          "refId": "A"
        },
        "titleFormat": "Deployment: {{ service }}",
        "showIn": 0,
        "tags": ["deployment"]
      }
    ]
  },
  "editable": true,
  "gnetId": null,
  "graphTooltip": 1,
  "id": 1,
  "links": [],
  "panels": [
    {
      "datasource": "prometheus",
      "description": "Overall service health status across all monitored services",
      "fieldConfig": {
        "defaults": {
          "color": {
            "mode": "thresholds"
          },
          "mappings": [
            {
              "options": {
                "0": {
                  "color": "red",
                  "index": 0,
                  "text": "DOWN"
                },
                "1": {
                  "color": "green",
                  "index": 1,
                  "text": "UP"
                }
              },
              "type": "value"
            }
          ],
          "max": 1,
          "min": 0,
          "thresholds": {
            "mode": "absolute",
            "steps": [
              {
                "color": "red",
                "value": null
              },
              {
                "color": "green",
                "value": 1
              }
            ]
          },
          "unit": "none"
        }
      },
      "gridPos": {
        "h": 8,
        "w": 6,
        "x": 0,
        "y": 0
      },
      "id": 1,
      "options": {
        "colorMode": "background",
        "graphMode": "none",
        "justifyMode": "center",
        "orientation": "horizontal",
        "reduceOptions": {
          "calcs": ["lastNotNull"],
          "fields": "",
          "values": false
        },
        "textMode": "auto"
      },
      "pluginVersion": "8.0.0",
      "targets": [
        {
          "expr": "up{job=~\"$service\",environment=~\"$environment\"}",
          "instant": false,
          "interval": "",
          "legendFormat": "{{ instance }}",
          "refId": "A"
        }
      ],
      "title": "Service Status",
      "type": "stat"
    },
    {
      "datasource": "prometheus",
      "description": "Request rate across all services",
      "fieldConfig": {
        "defaults": {
          "color": {
            "mode": "palette-classic"
          },
          "custom": {
            "axisLabel": "",
            "axisPlacement": "auto",
            "barAlignment": 0,
            "drawStyle": "line",
            "fillOpacity": 10,
            "gradientMode": "none",
            "hideFrom": {
              "graph": false,
              "legend": false,
              "tooltip": false
            },
            "lineInterpolation": "linear",
            "lineWidth": 1,
            "pointSize": 5,
            "scaleDistribution": {
              "type": "linear"
            },
            "showPoints": "never",
            "spanNulls": true
          },
          "mappings": [],
          "thresholds": {
            "mode": "absolute",
            "steps": [
              {
                "color": "green",
                "value": null
              },
              {
                "color": "red",
                "value": 80
              }
            ]
          },
          "unit": "reqps"
        }
      },
      "gridPos": {
        "h": 8,
        "w": 18,
        "x": 6,
        "y": 0
      },
      "id": 2,
      "options": {
        "legend": {
          "calcs": [],
          "displayMode": "list",
          "placement": "bottom"
        },
        "tooltip": {
          "mode": "single"
        }
      },
      "targets": [
        {
          "expr": "sum(rate(http_requests_total{job=~\"$service\",environment=~\"$environment\"}[5m])) by (service)",
          "interval": "",
          "legendFormat": "{{ service }}",
          "refId": "A"
        }
      ],
      "title": "Request Rate (req/sec)",
      "type": "timeseries"
    },
    {
      "datasource": "prometheus",
      "description": "Error rate percentage across all services",
      "fieldConfig": {
        "defaults": {
          "color": {
            "mode": "palette-classic"
          },
          "custom": {
            "axisLabel": "",
            "axisPlacement": "auto",
            "barAlignment": 0,
            "drawStyle": "line",
            "fillOpacity": 10,
            "gradientMode": "none",
            "hideFrom": {
              "graph": false,
              "legend": false,
              "tooltip": false
            },
            "lineInterpolation": "linear",
            "lineWidth": 1,
            "pointSize": 5,
            "scaleDistribution": {
              "type": "linear"
            },
            "showPoints": "never",
            "spanNulls": true
          },
          "mappings": [],
          "max": 100,
          "min": 0,
          "thresholds": {
            "mode": "absolute",
            "steps": [
              {
                "color": "green",
                "value": null
              },
              {
                "color": "yellow",
                "value": 1
              },
              {
                "color": "red",
                "value": 5
              }
            ]
          },
          "unit": "percent"
        }
      },
      "gridPos": {
        "h": 8,
        "w": 12,
        "x": 0,
        "y": 8
      },
      "id": 3,
      "options": {
        "legend": {
          "calcs": [],
          "displayMode": "list",
          "placement": "bottom"
        },
        "tooltip": {
          "mode": "single"
        }
      },
      "targets": [
        {
          "expr": "100 * sum(rate(http_requests_total{job=~\"$service\",environment=~\"$environment\",code=~\"5..\"}[5m])) by (service) / sum(rate(http_requests_total{job=~\"$service\",environment=~\"$environment\"}[5m])) by (service)",
          "interval": "",
          "legendFormat": "{{ service }}",
          "refId": "A"
        }
      ],
      "title": "Error Rate (%)",
      "type": "timeseries"
    },
    {
      "datasource": "prometheus",
      "description": "95th percentile response time across all services",
      "fieldConfig": {
        "defaults": {
          "color": {
            "mode": "palette-classic"
          },
          "custom": {
            "axisLabel": "",
            "axisPlacement": "auto",
            "barAlignment": 0,
            "drawStyle": "line",
            "fillOpacity": 10,
            "gradientMode": "none",
            "hideFrom": {
              "graph": false,
              "legend": false,
              "tooltip": false
            },
            "lineInterpolation": "linear",
            "lineWidth": 1,
            "pointSize": 5,
            "scaleDistribution": {
              "type": "linear"
            },
            "showPoints": "never",
            "spanNulls": true
          },
          "mappings": [],
          "thresholds": {
            "mode": "absolute",
            "steps": [
              {
                "color": "green",
                "value": null
              },
              {
                "color": "yellow",
                "value": 500
              },
              {
                "color": "red",
                "value": 1000
              }
            ]
          },
          "unit": "ms"
        }
      },
      "gridPos": {
        "h": 8,
        "w": 12,
        "x": 12,
        "y": 8
      },
      "id": 4,
      "options": {
        "legend": {
          "calcs": [],
          "displayMode": "list",
          "placement": "bottom"
        },
        "tooltip": {
          "mode": "single"
        }
      },
      "targets": [
        {
          "expr": "histogram_quantile(0.95, sum(rate(http_request_duration_seconds_bucket{job=~\"$service\",environment=~\"$environment\"}[5m])) by (le, service)) * 1000",
          "interval": "",
          "legendFormat": "{{ service }}",
          "refId": "A"
        }
      ],
      "title": "Response Time 95th Percentile (ms)",
      "type": "timeseries"
    },
    {
      "datasource": "prometheus",
      "description": "Current CPU usage across all services",
      "fieldConfig": {
        "defaults": {
          "color": {
            "mode": "thresholds"
          },
          "mappings": [],
          "max": 100,
          "min": 0,
          "thresholds": {
            "mode": "absolute",
            "steps": [
              {
                "color": "green",
                "value": null
              },
              {
                "color": "yellow",
                "value": 70
              },
              {
                "color": "red",
                "value": 85
              }
            ]
          },
          "unit": "percent"
        }
      },
      "gridPos": {
        "h": 8,
        "w": 8,
        "x": 0,
        "y": 16
      },
      "id": 5,
      "options": {
        "displayMode": "gradient",
        "orientation": "horizontal",
        "reduceOptions": {
          "calcs": ["lastNotNull"],
          "fields": "",
          "values": false
        },
        "showUnfilled": true
      },
      "pluginVersion": "8.0.0",
      "targets": [
        {
          "expr": "100 - (avg(irate(node_cpu_seconds_total{mode=\"idle\",job=~\"$service\",environment=~\"$environment\"}[5m])) by (instance) * 100)",
          "interval": "",
          "legendFormat": "{{ instance }}",
          "refId": "A"
        }
      ],
      "title": "CPU Usage (%)",
      "type": "bargauge"
    },
    {
      "datasource": "prometheus",
      "description": "Current memory usage across all services",
      "fieldConfig": {
        "defaults": {
          "color": {
            "mode": "thresholds"
          },
          "mappings": [],
          "max": 100,
          "min": 0,
          "thresholds": {
            "mode": "absolute",
            "steps": [
              {
                "color": "green",
                "value": null
              },
              {
                "color": "yellow",
                "value": 75
              },
              {
                "color": "red",
                "value": 90
              }
            ]
          },
          "unit": "percent"
        }
      },
      "gridPos": {
        "h": 8,
        "w": 8,
        "x": 8,
        "y": 16
      },
      "id": 6,
      "options": {
        "displayMode": "gradient",
        "orientation": "horizontal",
        "reduceOptions": {
          "calcs": ["lastNotNull"],
          "fields": "",
          "values": false
        },
        "showUnfilled": true
      },
      "pluginVersion": "8.0.0",
      "targets": [
        {
          "expr": "100 * (1 - node_memory_MemAvailable_bytes{job=~\"$service\",environment=~\"$environment\"} / node_memory_MemTotal_bytes{job=~\"$service\",environment=~\"$environment\"})",
          "interval": "",
          "legendFormat": "{{ instance }}",
          "refId": "A"
        }
      ],
      "title": "Memory Usage (%)",
      "type": "bargauge"
    },
    {
      "datasource": "prometheus",
      "description": "Current disk usage across all services",
      "fieldConfig": {
        "defaults": {
          "color": {
            "mode": "thresholds"
          },
          "mappings": [],
          "max": 100,
          "min": 0,
          "thresholds": {
            "mode": "absolute",
            "steps": [
              {
                "color": "green",
                "value": null
              },
              {
                "color": "yellow",
                "value": 80
              },
              {
                "color": "red",
                "value": 95
              }
            ]
          },
          "unit": "percent"
        }
      },
      "gridPos": {
        "h": 8,
        "w": 8,
        "x": 16,
        "y": 16
      },
      "id": 7,
      "options": {
        "displayMode": "gradient",
        "orientation": "horizontal",
        "reduceOptions": {
          "calcs": ["lastNotNull"],
          "fields": "",
          "values": false
        },
        "showUnfilled": true
      },
      "pluginVersion": "8.0.0",
      "targets": [
        {
          "expr": "100 * (1 - node_filesystem_avail_bytes{job=~\"$service\",environment=~\"$environment\",fstype!=\"tmpfs\"} / node_filesystem_size_bytes{job=~\"$service\",environment=~\"$environment\",fstype!=\"tmpfs\"})",
          "interval": "",
          "legendFormat": "{{ instance }}:{{ mountpoint }}",
          "refId": "A"
        }
      ],
      "title": "Disk Usage (%)",
      "type": "bargauge"
    },
    {
      "datasource": "prometheus",
      "description": "Top 10 slowest endpoints by response time",
      "fieldConfig": {
        "defaults": {
          "color": {
            "mode": "palette-classic"
          },
          "custom": {
            "displayMode": "table",
            "filterable": false
          },
          "mappings": [],
          "thresholds": {
            "mode": "absolute",
            "steps": [
              {
                "color": "green",
                "value": null
              },
              {
                "color": "red",
                "value": 80
              }
            ]
          },
          "unit": "ms"
        }
      },
      "gridPos": {
        "h": 8,
        "w": 12,
        "x": 0,
        "y": 24
      },
      "id": 8,
      "options": {
        "showHeader": true,
        "sortBy": [
          {
            "desc": true,
            "displayName": "Value"
          }
        ]
      },
      "pluginVersion": "8.0.0",
      "targets": [
        {
          "expr": "topk(10, histogram_quantile(0.95, sum(rate(http_request_duration_seconds_bucket{job=~\"$service\",environment=~\"$environment\"}[5m])) by (le, handler)) * 1000)",
          "format": "table",
          "instant": true,
          "interval": "",
          "legendFormat": "",
          "refId": "A"
        }
      ],
      "title": "Top 10 Slowest Endpoints",
      "type": "table"
    },
    {
      "datasource": "prometheus",
      "description": "Recent errors by service and endpoint",
      "fieldConfig": {
        "defaults": {
          "color": {
            "mode": "palette-classic"
          },
          "custom": {
            "displayMode": "table",
            "filterable": true
          },
          "mappings": [],
          "thresholds": {
            "mode": "absolute",
            "steps": [
              {
                "color": "green",
                "value": null
              },
              {
                "color": "red",
                "value": 80
              }
            ]
          },
          "unit": "reqps"
        }
      },
      "gridPos": {
        "h": 8,
        "w": 12,
        "x": 12,
        "y": 24
      },
      "id": 9,
      "options": {
        "showHeader": true,
        "sortBy": [
          {
            "desc": true,
            "displayName": "Value"
          }
        ]
      },
      "pluginVersion": "8.0.0",
      "targets": [
        {
          "expr": "sum(rate(http_requests_total{job=~\"$service\",environment=~\"$environment\",code=~\"5..\"}[5m])) by (service, handler, code) > 0",
          "format": "table",
          "instant": true,
          "interval": "",
          "legendFormat": "",
          "refId": "A"
        }
      ],
      "title": "Recent Errors",
      "type": "table"
    }
  ],
  "refresh": "30s",
  "schemaVersion": 27,
  "style": "dark",
  "tags": ["universal-platform", "overview", "monitoring"],
  "templating": {
    "list": [
      {
        "current": {
          "selected": false,
          "text": "All",
          "value": "$__all"
        },
        "datasource": "prometheus",
        "definition": "label_values(up, job)",
        "description": null,
        "error": null,
        "hide": 0,
        "includeAll": true,
        "label": "Service",
        "multi": true,
        "name": "service",
        "options": [],
        "query": {
          "query": "label_values(up, job)",
          "refId": "StandardVariableQuery"
        },
        "refresh": 1,
        "regex": "",
        "skipUrlSync": false,
        "sort": 1,
        "type": "query"
      },
      {
        "current": {
          "selected": false,
          "text": "All",
          "value": "$__all"
        },
        "datasource": "prometheus",
        "definition": "label_values(up{job=~\"$service\"}, environment)",
        "description": null,
        "error": null,
        "hide": 0,
        "includeAll": true,
        "label": "Environment",
        "multi": true,
        "name": "environment",
        "options": [],
        "query": {
          "query": "label_values(up{job=~\"$service\"}, environment)",
          "refId": "StandardVariableQuery"
        },
        "refresh": 1,
        "regex": "",
        "skipUrlSync": false,
        "sort": 1,
        "type": "query"
      }
    ]
  },
  "time": {
    "from": "now-1h",
    "to": "now"
  },
  "timepicker": {},
  "timezone": "",
  "title": "Universal Platform - Service Overview",
  "uid": "universal-platform-overview",
  "version": 1,
  "description": "Comprehensive service overview dashboard for the Universal Project Platform showing key performance indicators, infrastructure health, and error tracking across all monitored services."
}
